openapi_lookup/__init__.py
openapi_lookup/cli.py
openapi_lookup/openapis.py
openapi_lookup-0.1.1.dist-info/LICENSE
openapi_lookup-0.1.1.dist-info/METADATA
openapi_lookup-0.1.1.dist-info/WHEEL
openapi_lookup-0.1.1.dist-info/entry_points.txt
openapi_lookup-0.1.1.dist-info/RECORD
